finanfut_billing_sdk/__init__.py
finanfut_billing_sdk/client.py
finanfut_billing_sdk/errors.py
finanfut_billing_sdk/models.py
finanfut_billing_sdk/providers.py
finanfut_billing_sdk/version.py
finanfut_billing_sdk-2.1.11.dist-info/licenses/LICENSE
finanfut_billing_sdk-2.1.11.dist-info/METADATA
finanfut_billing_sdk-2.1.11.dist-info/WHEEL
finanfut_billing_sdk-2.1.11.dist-info/top_level.txt
finanfut_billing_sdk-2.1.11.dist-info/RECORD
