Metadata-Version: 2.4
Name: finanfut-billing-sdk
Version: 2.1.11
Summary: Python SDK for Finanfut Billing External API
Author: Finanfut
License: MIT License
Project-URL: Homepage, https://finanfut.com
Project-URL: Source, https://github.com/finanfut/finanfut-billing
Requires-Python: >=3.9
License-File: LICENSE
Requires-Dist: pydantic<3.0,>=2.0
Requires-Dist: requests>=2.31
Dynamic: license-file
